smo_rejection/__init__.py
smo_rejection/exception.py
smo_rejection/models.py
smo_rejection/pdf_export.py
smo_rejection/processing.py
smo_rejection/simulation.py
smo_rejection/utils.py
smo_rejection/xml_export.py
smo_rejection-0.5.6.dist-info/METADATA
smo_rejection-0.5.6.dist-info/WHEEL
smo_rejection-0.5.6.dist-info/RECORD
