Metadata-Version: 2.1
Name: smo_rejection
Version: 0.5.6
Summary: 
Author: mbtmrw
Author-email: keks2324098@gmail.com
Requires-Python: >=3.11,<4.0
Classifier: Programming Language :: Python :: 3
Classifier: Programming Language :: Python :: 3.11
Classifier: Programming Language :: Python :: 3.12
Requires-Dist: openpyxl (>=3.1.2,<4.0.0)
Requires-Dist: reportlab (>=4.2.0,<5.0.0)
